[
  {
    "path": "posts/2020-08-29-building-website-with-distill-r/",
    "title": "Building Website with Distill Package in R",
    "description": "I never thought before that creating a website would be this fun.",
    "author": [
      {
        "name": "Dewi Lestari Amaliah",
        "url": {}
      }
    ],
    "date": "2020-08-29",
    "categories": [
      "Rmarkdown"
    ],
    "preview": "posts/2020-08-29-building-website-with-distill-r/arnel-hasanovic-MNd-Rka1o0Q-unsplash.JPG",
    "last_modified": "2020-08-29T15:00:59+10:00",
    "input_file": {}
  }
]
